LICENSE
README.md
setup.py
fedlab/__init__.py
fedlab.egg-info/PKG-INFO
fedlab.egg-info/SOURCES.txt
fedlab.egg-info/dependency_links.txt
fedlab.egg-info/requires.txt
fedlab.egg-info/top_level.txt
fedlab/contrib/__init__.py
fedlab/contrib/algorithm/__init__.py
fedlab/contrib/algorithm/basic_client.py
fedlab/contrib/algorithm/basic_server.py
fedlab/contrib/algorithm/ditto.py
fedlab/contrib/algorithm/fedavg.py
fedlab/contrib/algorithm/feddyn.py
fedlab/contrib/algorithm/fednova.py
fedlab/contrib/algorithm/fedprox.py
fedlab/contrib/algorithm/ifca.py
fedlab/contrib/algorithm/powerofchoice.py
fedlab/contrib/algorithm/qfedavg.py
fedlab/contrib/algorithm/scaffold.py
fedlab/contrib/compressor/__init__.py
fedlab/contrib/compressor/compressor.py
fedlab/contrib/compressor/quantization.py
fedlab/contrib/compressor/topk.py
fedlab/contrib/dataset/__init__.py
fedlab/contrib/dataset/adult.py
fedlab/contrib/dataset/basic_dataset.py
fedlab/contrib/dataset/celeba.py
fedlab/contrib/dataset/covtype.py
fedlab/contrib/dataset/fcube.py
fedlab/contrib/dataset/femnist.py
fedlab/contrib/dataset/partitioned_cifar10.py
fedlab/contrib/dataset/partitioned_mnist.py
fedlab/contrib/dataset/pathological_mnist.py
fedlab/contrib/dataset/rcv1.py
fedlab/contrib/dataset/rotated_cifar10.py
fedlab/contrib/dataset/rotated_mnist.py
fedlab/contrib/dataset/sent140.py
fedlab/contrib/dataset/shakespeare.py
fedlab/core/__init__.py
fedlab/core/coordinator.py
fedlab/core/model_maintainer.py
fedlab/core/network.py
fedlab/core/network_manager.py
fedlab/core/standalone.py
fedlab/core/client/__init__.py
fedlab/core/client/manager.py
fedlab/core/client/trainer.py
fedlab/core/communicator/__init__.py
fedlab/core/communicator/package.py
fedlab/core/communicator/processor.py
fedlab/core/server/__init__.py
fedlab/core/server/handler.py
fedlab/core/server/manager.py
fedlab/core/server/hierarchical/__init__.py
fedlab/core/server/hierarchical/connector.py
fedlab/core/server/hierarchical/scheduler.py
fedlab/models/__init__.py
fedlab/models/cnn.py
fedlab/models/mlp.py
fedlab/models/rnn.py
fedlab/utils/__init__.py
fedlab/utils/aggregator.py
fedlab/utils/functional.py
